tsutsuji/__init__.py
tsutsuji/__main__.py
tsutsuji/_version.py
tsutsuji/backimg.py
tsutsuji/backimg_height.py
tsutsuji/config.py
tsutsuji/cui2.py
tsutsuji/curvetrackplot.py
tsutsuji/drawcursor.py
tsutsuji/gui_tsutsuji.py
tsutsuji/heightmeasure.py
tsutsuji/heightsolver.py
tsutsuji/heightwindow.py
tsutsuji/kml2track.py
tsutsuji/kp_handling.py
tsutsuji/kp_offset.py
tsutsuji/math.py
tsutsuji/measure.py
tsutsuji/mediantrack.py
tsutsuji/solver.py
tsutsuji/track_control.py
tsutsuji/trackwindow.py
tsutsuji_trackcomputer-1.9.3.dist-info/licenses/LICENSE
tsutsuji_trackcomputer-1.9.3.dist-info/METADATA
tsutsuji_trackcomputer-1.9.3.dist-info/WHEEL
tsutsuji_trackcomputer-1.9.3.dist-info/top_level.txt
tsutsuji_trackcomputer-1.9.3.dist-info/RECORD
