Metadata-Version: 2.4
Name: tsutsuji-trackcomputer
Version: 1.9.3
Summary: Track building helper for Bve trainsim 5/6
Home-page: https://github.com/konawasabi/tsutsuji-trackcomputer/
Author: Konawasabi
Author-email: webmaster@konawasabi.riceball.jp
License: Apache License 2.0
Keywords: BVE trainsim
License-File: LICENSE
Requires-Dist: kobushi-trackviewer>=1.2.2
Requires-Dist: requests>=2.28.1
Requires-Dist: matplotlib>=3.9.1
Requires-Dist: Pyqtree>=1.0.0
Dynamic: license-file
